koopmans/__init__.py
koopmans/bands.py
koopmans/cell.py
koopmans/commands.py
koopmans/files.py
koopmans/kpoints.py
koopmans/mpl_config.py
koopmans/outputs.py
koopmans/projections.py
koopmans/pseudopotentials.py
koopmans/qei_to_json.py
koopmans/references.bib
koopmans/references.py
koopmans/calculators/__init__.py
koopmans/calculators/_calculator.py
koopmans/calculators/_environ.py
koopmans/calculators/_koopmans_cp.py
koopmans/calculators/_koopmans_ham.py
koopmans/calculators/_koopmans_screen.py
koopmans/calculators/_ph.py
koopmans/calculators/_projwfc.py
koopmans/calculators/_pw.py
koopmans/calculators/_pw2wannier.py
koopmans/calculators/_wann2kc.py
koopmans/calculators/_wann2kcp.py
koopmans/calculators/_wannier90.py
koopmans/cli/__init__.py
koopmans/cli/main.py
koopmans/io/__init__.py
koopmans/io/_calculators.py
koopmans/io/_dill.py
koopmans/io/_generic.py
koopmans/io/_json.py
koopmans/ml/__init__.py
koopmans/ml/_basis_functions.py
koopmans/ml/_compute_decomposition.py
koopmans/ml/_compute_power.py
koopmans/ml/_misc.py
koopmans/ml/_ml_models.py
koopmans/ml/_precompute_parameters_of_basis.py
koopmans/processes/__init__.py
koopmans/processes/_commandlinetool.py
koopmans/processes/_process.py
koopmans/processes/bin2xml.py
koopmans/processes/koopmans_cp.py
koopmans/processes/merge_evc.py
koopmans/processes/power_spectrum.py
koopmans/processes/wannier.py
koopmans/processes/ui/__init__.py
koopmans/processes/ui/_atoms.py
koopmans/processes/ui/_process.py
koopmans/processes/ui/_utils.py
koopmans/pseudopotentials/generate_wfc_psps.py
koopmans/pseudopotentials/pseudo_dojo_standard_v0.4.1/lda/Ag.upf
koopmans/pseudopotentials/pseudo_dojo_standard_v0.4.1/lda/Al.upf
koopmans/pseudopotentials/pseudo_dojo_standard_v0.4.1/lda/Ar.upf
koopmans/pseudopotentials/pseudo_dojo_standard_v0.4.1/lda/As.upf
koopmans/pseudopotentials/pseudo_dojo_standard_v0.4.1/lda/Au.upf
koopmans/pseudopotentials/pseudo_dojo_standard_v0.4.1/lda/B.upf
koopmans-1.1.0.dist-info/LICENSE
koopmans-1.1.0.dist-info/METADATA
koopmans-1.1.0.dist-info/WHEEL
koopmans-1.1.0.dist-info/entry_points.txt
koopmans-1.1.0.dist-info/top_level.txt
koopmans-1.1.0.dist-info/RECORD
