Metadata-Version: 2.2
Name: koopmans
Version: 1.1.0
Summary: Koopmans spectral functional calculations with python and Quantum ESPRESSO
Author-email: Edward Linscott <edward.linscott@epfl.ch>, Riccardo De Gennaro <riccardo.degennaro@epfl.ch>, Nicola Colonna <nicola.colonna@psi.ch>
Project-URL: homepage, https://koopmans-functionals.org/
Project-URL: repository, https://github.com/epfl-theos/koopmans
Project-URL: google-group, https://groups.google.com/g/koopmans-users
Classifier: Intended Audience :: Science/Research
Classifier: License :: OSI Approved :: GNU General Public License v2 (GPLv2)
Classifier: Programming Language :: Python :: 3
Classifier: Programming Language :: Python :: 3.10
Classifier: Programming Language :: Python :: 3.11
Classifier: Programming Language :: Python :: 3.12
Classifier: Topic :: Scientific/Engineering
Classifier: Topic :: Scientific/Engineering :: Chemistry
Classifier: Topic :: Scientific/Engineering :: Physics
Requires-Python: >=3.10
License-File: LICENSE
Requires-Dist: matplotlib>=3.5.1
Requires-Dist: scipy>=0.18.1
Requires-Dist: numpy>=1.21
Requires-Dist: argparse>=1.1
Requires-Dist: pandas>=1.0.0
Requires-Dist: typing>=3.6
Requires-Dist: pybtex>=0.24
Requires-Dist: spglib>=1.9
Requires-Dist: upf-to-json>=0.9.5
Requires-Dist: ase-koopmans==0.1.6
Requires-Dist: scikit-learn>=1.0
Requires-Dist: deepdiff>=5.8.1
Requires-Dist: pydantic>=2.7.0
Requires-Dist: dill>=0.3.8
Requires-Dist: tabulate==0.9.0
Provides-Extra: test
Requires-Dist: codecov>=2.0; extra == "test"
Requires-Dist: coverage>=4.4; extra == "test"
Requires-Dist: hypothesis>=6.0.0; extra == "test"
Requires-Dist: pytest>=5.4; extra == "test"
Requires-Dist: pytest-cov>=2.9; extra == "test"
Provides-Extra: docs
Requires-Dist: sphinx>=3.0; extra == "docs"
Requires-Dist: sphinxcontrib-bibtex>=2.1.4; extra == "docs"
Requires-Dist: sphinx_toolbox>=2.5.0; extra == "docs"
Requires-Dist: sphinx_rtd_theme>=1.0.0; extra == "docs"
Requires-Dist: recommonmark>=0.7.1; extra == "docs"
Requires-Dist: numpydoc>=1.4.0; extra == "docs"
Requires-Dist: sphinx-pyproject>=0.1.0; extra == "docs"
